easelenium/__init__.py
easelenium/base_page_object.py
easelenium/base_test.py
easelenium/browser.py
easelenium/mouse.py
easelenium/utils.py
easelenium/licenses/easelenium_license.txt
easelenium/licenses/firebug_license.txt
easelenium/scripts/easelenium_cli.py
easelenium/scripts/easelenium_ui.py
easelenium/ui/__init__.py
easelenium/ui/context_menu.py
easelenium/ui/file_utils.py
easelenium/ui/main_ui.py
easelenium/ui/root_folder.py
easelenium/ui/string_utils.py
easelenium/ui/test_runner_ui.py
easelenium/ui/utils.py
easelenium/ui/editor/__init__.py
easelenium/ui/editor/editor_ui.py
easelenium/ui/editor/field_context_menu.py
easelenium/ui/editor/utils.py
easelenium/ui/generator/__init__.py
easelenium/ui/generator/generator_ui.py
easelenium/ui/generator/get_xpath.js
easelenium/ui/generator/page_object_class.py
easelenium/ui/generator/page_object_generator.py
easelenium/ui/parser/__init__.py
easelenium/ui/parser/parsed_class.py
easelenium/ui/selector_finder/__init__.py
easelenium/ui/selector_finder/finder_ui.py
easelenium/ui/widgets/__init__.py
easelenium/ui/widgets/table.py
easelenium/ui/widgets/utils.py
easelenium/ui/widgets/image/__init__.py
easelenium/ui/widgets/image/image_panel.py
easelenium/ui/widgets/image/image_with_elements.py
easelenium/ui/widgets/image/selectable_image.py
easelenium-0.7.2.dist-info/METADATA
easelenium-0.7.2.dist-info/WHEEL
easelenium-0.7.2.dist-info/entry_points.txt
easelenium-0.7.2.dist-info/top_level.txt
easelenium-0.7.2.dist-info/RECORD
