Metadata-Version: 2.1
Name: easelenium
Version: 0.7.2
Summary: easelenium - Selenium-based Test Automation Framework.
Author-email: Kirill Strelkov <kirillstrelkov@users.noreply.github.com>
Requires-Python: >=3.8
Requires-Dist: wheel
Requires-Dist: selenium
Requires-Dist: attrdict3
Requires-Dist: pytest
Requires-Dist: pytest-html
Requires-Dist: loguru
Requires-Dist: webdriver-manager
Requires-Dist: wxPython
